polars_game_of_life-0.1.0.dist-info/METADATA
polars_game_of_life-0.1.0.dist-info/WHEEL
polars_game_of_life-0.1.0.dist-info/license_files/LICENSE
game_of_life/__init__.py
game_of_life/utils.py
game_of_life/game_of_life.abi3.so
polars_game_of_life-0.1.0.dist-info/RECORD
