Metadata-Version: 2.3
Name: polars-game-of-life
Version: 0.1.0
Classifier: Development Status :: 3 - Alpha
Classifier: Intended Audience :: Developers
Classifier: License :: OSI Approved :: Apache Software License
Classifier: Programming Language :: Python :: 3
Classifier: Programming Language :: Rust
Classifier: Programming Language :: Python :: Implementation :: CPython
Classifier: Programming Language :: Python :: Implementation :: PyPy
Requires-Dist: polars >=0.41.3
Requires-Dist: pytest >=8.2.2 ; extra == 'dev'
Requires-Dist: mypy >=1.10.1 ; extra == 'dev'
Requires-Dist: ruff >=0.5.0 ; extra == 'dev'
Requires-Dist: maturin >=1.6.0 ; extra == 'dev'
Provides-Extra: dev
License-File: LICENSE
Summary: A polars plugin to showcase some features of the plugin system.
Keywords: conway,life,rust,python,polars,plugin
Author: Bruno Conde Kind
Requires-Python: >=3.11
Project-URL: Homepage, https://github.com/condekind/life_polars_plugin
Project-URL: Documentation, https://github.com/condekind/life_polars_plugin
Project-URL: Repository, https://github.com/condekind/life_polars_plugin
Project-URL: Bug-Tracker, https://github.com/condekind/life_polars_plugin/issues
